LICENSE
README.md
setup.py
looker_ingestion/__init__.py
looker_ingestion/exceptions.py
looker_ingestion/load_s3.py
looker_ingestion/sync_data.py
looker_ingestion.egg-info/PKG-INFO
looker_ingestion.egg-info/SOURCES.txt
looker_ingestion.egg-info/dependency_links.txt
looker_ingestion.egg-info/entry_points.txt
looker_ingestion.egg-info/requires.txt
looker_ingestion.egg-info/top_level.txt
tests/__init__.py
tests/test_load_s3.py
tests/test_sync_data.py