Metadata-Version: 2.1
Name: looker-ingestion
Version: 1.1.5
Summary: Extracts adhoc queries from the Looker API to S3
Home-page: https://github.com/open-toast/extract-looker-metadata
License: UNKNOWN
Platform: UNKNOWN
Classifier: Intended Audience :: Developers
Classifier: Programming Language :: Python :: 3
License-File: LICENSE
